figctx/__init__.py
figctx/context.py
figctx/palette.py
figctx-0.1.2.dist-info/licenses/LICENSE
figctx-0.1.2.dist-info/METADATA
figctx-0.1.2.dist-info/WHEEL
figctx-0.1.2.dist-info/top_level.txt
figctx-0.1.2.dist-info/RECORD
