Metadata-Version: 2.4
Name: figctx
Version: 0.1.2
Summary: Figure context manager for QuiME Lab
Author-email: Lee Chan-yeong <ckckdud123@gmail.com>
License: MIT
Project-URL: Homepage, https://github.com/ckckdud3/figctx
Requires-Python: >=3.8
License-File: LICENSE
Requires-Dist: matplotlib>=3.3
Provides-Extra: test
Requires-Dist: pytest; extra == "test"
Requires-Dist: pytest-cov; extra == "test"
Dynamic: license-file
